{
  "created_at_utc": "2026-05-12T22:14:27.854007+00:00",
  "gate": {
    "baseline_method_id": "M4",
    "harm_tolerance": 0.0,
    "min_step_norm_ratio": 0.5,
    "worst_tolerance": 0.0
  },
  "inputs": [
    "docs/results/phase0_boltz2_oracle_gradient_conflict_23bc3a1_20260510T220950Z.json",
    "docs/results/phase0_boltz2_oracle_gradient_conflict_23bc3a1_20260510T224007Z.json",
    "docs/results/phase0_boltz2_oracle_gradient_conflict_23bc3a1_20260510T231100Z.json",
    "docs/results/phase0_boltz2_oracle_gradient_conflict_23bc3a1_20260510T234048Z.json",
    "docs/results/phase0_boltz2_oracle_gradient_conflict_23bc3a1_20260511T001153Z.json"
  ],
  "overall": [
    {
      "gate_checks": {
        "boltz2_descent": true,
        "harm_no_worse": true,
        "protenix_descent": true,
        "step_nontrivial": true,
        "worst_no_worse": true
      },
      "gate_decision": "baseline",
      "mean_boltz2_directional_derivative": -0.07192706009373069,
      "mean_oracle_harm_rate": 0.0,
      "mean_protenix_directional_derivative": -1.8416703663766385,
      "mean_step_norm": 0.5022839322686196,
      "mean_worst_oracle_directional_derivative": -0.013477584347128868,
      "method": "normalized_weighted",
      "method_id": "M4",
      "num_rows": 20,
      "num_seeds": 4,
      "num_targets": 5,
      "zero_harm": true,
      "zero_harm_targets": 5
    },
    {
      "gate_checks": {
        "boltz2_descent": true,
        "harm_no_worse": false,
        "protenix_descent": true,
        "step_nontrivial": true,
        "worst_no_worse": false
      },
      "gate_decision": "fail",
      "mean_boltz2_directional_derivative": -0.06694655018509366,
      "mean_oracle_harm_rate": 0.08,
      "mean_protenix_directional_derivative": -5.390254252403975,
      "mean_step_norm": 0.810299026966095,
      "mean_worst_oracle_directional_derivative": 0.004740161841618828,
      "method": "contact_preserving_soft_cone",
      "method_id": "M7c",
      "num_rows": 20,
      "num_seeds": 4,
      "num_targets": 5,
      "zero_harm": false,
      "zero_harm_targets": 1
    },
    {
      "gate_checks": {
        "boltz2_descent": true,
        "harm_no_worse": false,
        "protenix_descent": true,
        "step_nontrivial": true,
        "worst_no_worse": false
      },
      "gate_decision": "fail",
      "mean_boltz2_directional_derivative": -0.04386249310919084,
      "mean_oracle_harm_rate": 0.25,
      "mean_protenix_directional_derivative": -7.774297547340393,
      "mean_step_norm": 1.0425023689866066,
      "mean_worst_oracle_directional_derivative": 0.03525018925429322,
      "method": "naive_weighted",
      "method_id": "M3",
      "num_rows": 20,
      "num_seeds": 4,
      "num_targets": 5,
      "zero_harm": false,
      "zero_harm_targets": 0
    },
    {
      "gate_checks": {
        "boltz2_descent": true,
        "harm_no_worse": false,
        "protenix_descent": true,
        "step_nontrivial": true,
        "worst_no_worse": false
      },
      "gate_decision": "fail",
      "mean_boltz2_directional_derivative": -0.03010196564719081,
      "mean_oracle_harm_rate": 0.39,
      "mean_protenix_directional_derivative": -7.26936012506485,
      "mean_step_norm": 0.9463940888643265,
      "mean_worst_oracle_directional_derivative": 0.03536543708760291,
      "method": "contact_qp_grid",
      "method_id": "M8a",
      "num_rows": 20,
      "num_seeds": 4,
      "num_targets": 5,
      "zero_harm": false,
      "zero_harm_targets": 0
    }
  ],
  "per_target": [
    {
      "mean_boltz2_directional_derivative": -0.03563202545046806,
      "mean_oracle_harm_rate": 0.30000000000000004,
      "mean_protenix_directional_derivative": -2.259097397327423,
      "mean_step_norm": 0.6968100816011429,
      "mean_worst_oracle_directional_derivative": 0.06438667699694633,
      "method": "naive_weighted",
      "method_id": "M3",
      "num_rows": 4,
      "num_seeds": 4,
      "target": "1ALU:A",
      "zero_harm": false
    },
    {
      "mean_boltz2_directional_derivative": -0.04489399306476116,
      "mean_oracle_harm_rate": 0.0,
      "mean_protenix_directional_derivative": -0.6873262338340282,
      "mean_step_norm": 0.48667219281196594,
      "mean_worst_oracle_directional_derivative": -0.014327426790259778,
      "method": "normalized_weighted",
      "method_id": "M4",
      "num_rows": 4,
      "num_seeds": 4,
      "target": "1ALU:A",
      "zero_harm": true
    },
    {
      "mean_boltz2_directional_derivative": -0.04489399306476116,
      "mean_oracle_harm_rate": 0.0,
      "mean_protenix_directional_derivative": -0.6873262338340282,
      "mean_step_norm": 0.48667219281196594,
      "mean_worst_oracle_directional_derivative": -0.014327426790259778,
      "method": "contact_preserving_soft_cone",
      "method_id": "M7c",
      "num_rows": 4,
      "num_seeds": 4,
      "target": "1ALU:A",
      "zero_harm": true
    },
    {
      "mean_boltz2_directional_derivative": -0.017816341249272227,
      "mean_oracle_harm_rate": 0.35,
      "mean_protenix_directional_derivative": -1.3651343286037445,
      "mean_step_norm": 0.49213748052716255,
      "mean_worst_oracle_directional_derivative": 0.03174754977226257,
      "method": "contact_qp_grid",
      "method_id": "M8a",
      "num_rows": 4,
      "num_seeds": 4,
      "target": "1ALU:A",
      "zero_harm": false
    },
    {
      "mean_boltz2_directional_derivative": -0.0745164668187499,
      "mean_oracle_harm_rate": 0.15000000000000002,
      "mean_protenix_directional_derivative": -3.801726520061493,
      "mean_step_norm": 0.8489643782377243,
      "mean_worst_oracle_directional_derivative": 0.029456415431923233,
      "method": "naive_weighted",
      "method_id": "M3",
      "num_rows": 4,
      "num_seeds": 4,
      "target": "2JJS:C",
      "zero_harm": false
    },
    {
      "mean_boltz2_directional_derivative": -0.08637607796117663,
      "mean_oracle_harm_rate": 0.0,
      "mean_protenix_directional_derivative": -1.238265261054039,
      "mean_step_norm": 0.503692589700222,
      "mean_worst_oracle_directional_derivative": -0.0132658367510885,
      "method": "normalized_weighted",
      "method_id": "M4",
      "num_rows": 4,
      "num_seeds": 4,
      "target": "2JJS:C",
      "zero_harm": true
    },
    {
      "mean_boltz2_directional_derivative": -0.09383436990901828,
      "mean_oracle_harm_rate": 0.05,
      "mean_protenix_directional_derivative": -3.3484359234571457,
      "mean_step_norm": 0.7871840670704842,
      "mean_worst_oracle_directional_derivative": 0.013543459339416586,
      "method": "contact_preserving_soft_cone",
      "method_id": "M7c",
      "num_rows": 4,
      "num_seeds": 4,
      "target": "2JJS:C",
      "zero_harm": false
    },
    {
      "mean_boltz2_directional_derivative": -0.05395278334617615,
      "mean_oracle_harm_rate": 0.30000000000000004,
      "mean_protenix_directional_derivative": -3.80215060710907,
      "mean_step_norm": 0.8381533920764923,
      "mean_worst_oracle_directional_derivative": 0.031574676744639874,
      "method": "contact_qp_grid",
      "method_id": "M8a",
      "num_rows": 4,
      "num_seeds": 4,
      "target": "2JJS:C",
      "zero_harm": false
    },
    {
      "mean_boltz2_directional_derivative": -0.019397669471800327,
      "mean_oracle_harm_rate": 0.4,
      "mean_protenix_directional_derivative": -19.098050832748413,
      "mean_step_norm": 1.543252557516098,
      "mean_worst_oracle_directional_derivative": 0.012740022299112752,
      "method": "naive_weighted",
      "method_id": "M3",
      "num_rows": 4,
      "num_seeds": 4,
      "target": "4ZQK:A",
      "zero_harm": false
    },
    {
      "mean_boltz2_directional_derivative": -0.0491184601560235,
      "mean_oracle_harm_rate": 0.0,
      "mean_protenix_directional_derivative": -4.303651928901672,
      "mean_step_norm": 0.5071016177535057,
      "mean_worst_oracle_directional_derivative": -0.013721923809498549,
      "method": "normalized_weighted",
      "method_id": "M4",
      "num_rows": 4,
      "num_seeds": 4,
      "target": "4ZQK:A",
      "zero_harm": true
    },
    {
      "mean_boltz2_directional_derivative": -0.04500991362147033,
      "mean_oracle_harm_rate": 0.1,
      "mean_protenix_directional_derivative": -13.799427390098572,
      "mean_step_norm": 1.079932264983654,
      "mean_worst_oracle_directional_derivative": -0.005397516040829942,
      "method": "contact_preserving_soft_cone",
      "method_id": "M7c",
      "num_rows": 4,
      "num_seeds": 4,
      "target": "4ZQK:A",
      "zero_harm": false
    },
    {
      "mean_boltz2_directional_derivative": -0.016592770349234343,
      "mean_oracle_harm_rate": 0.45,
      "mean_protenix_directional_derivative": -19.059231281280518,
      "mean_step_norm": 1.5330409109592438,
      "mean_worst_oracle_directional_derivative": 0.014613102772273123,
      "method": "contact_qp_grid",
      "method_id": "M8a",
      "num_rows": 4,
      "num_seeds": 4,
      "target": "4ZQK:A",
      "zero_harm": false
    },
    {
      "mean_boltz2_directional_derivative": -0.08661219364148565,
      "mean_oracle_harm_rate": 0.2,
      "mean_protenix_directional_derivative": -6.650619804859161,
      "mean_step_norm": 1.0867985486984253,
      "mean_worst_oracle_directional_derivative": 0.010136903234524652,
      "method": "naive_weighted",
      "method_id": "M3",
      "num_rows": 4,
      "num_seeds": 4,
      "target": "4ZQK:B",
      "zero_harm": false
    },
    {
      "mean_boltz2_directional_derivative": -0.09657080378383398,
      "mean_oracle_harm_rate": 0.0,
      "mean_protenix_directional_derivative": -1.4668863117694855,
      "mean_step_norm": 0.5001841932535172,
      "mean_worst_oracle_directional_derivative": -0.01243488397449255,
      "method": "normalized_weighted",
      "method_id": "M4",
      "num_rows": 4,
      "num_seeds": 4,
      "target": "4ZQK:B",
      "zero_harm": true
    },
    {
      "mean_boltz2_directional_derivative": -0.08488875234615989,
      "mean_oracle_harm_rate": 0.2,
      "mean_protenix_directional_derivative": -6.659762918949127,
      "mean_step_norm": 1.0861406326293945,
      "mean_worst_oracle_directional_derivative": 0.025690897804452106,
      "method": "contact_preserving_soft_cone",
      "method_id": "M7c",
      "num_rows": 4,
      "num_seeds": 4,
      "target": "4ZQK:B",
      "zero_harm": false
    },
    {
      "mean_boltz2_directional_derivative": -0.04855742654763162,
      "mean_oracle_harm_rate": 0.45,
      "mean_protenix_directional_derivative": -6.696049213409424,
      "mean_step_norm": 1.0845845937728882,
      "mean_worst_oracle_directional_derivative": 0.052520737051963806,
      "method": "contact_qp_grid",
      "method_id": "M8a",
      "num_rows": 4,
      "num_seeds": 4,
      "target": "4ZQK:B",
      "zero_harm": false
    },
    {
      "mean_boltz2_directional_derivative": -0.003154110163450241,
      "mean_oracle_harm_rate": 0.2,
      "mean_protenix_directional_derivative": -7.061993181705475,
      "mean_step_norm": 1.0366862788796425,
      "mean_worst_oracle_directional_derivative": 0.05953092830895912,
      "method": "naive_weighted",
      "method_id": "M3",
      "num_rows": 4,
      "num_seeds": 4,
      "target": "IL7RA:A",
      "zero_harm": false
    },
    {
      "mean_boltz2_directional_derivative": -0.08267596550285816,
      "mean_oracle_harm_rate": 0.0,
      "mean_protenix_directional_derivative": -1.512222096323967,
      "mean_step_norm": 0.5137690678238869,
      "mean_worst_oracle_directional_derivative": -0.013637850410304964,
      "method": "normalized_weighted",
      "method_id": "M4",
      "num_rows": 4,
      "num_seeds": 4,
      "target": "IL7RA:A",
      "zero_harm": true
    },
    {
      "mean_boltz2_directional_derivative": -0.06610572198405862,
      "mean_oracle_harm_rate": 0.05,
      "mean_protenix_directional_derivative": -2.4563187956809998,
      "mean_step_norm": 0.6115659773349762,
      "mean_worst_oracle_directional_derivative": 0.00419139489531517,
      "method": "contact_preserving_soft_cone",
      "method_id": "M7c",
      "num_rows": 4,
      "num_seeds": 4,
      "target": "IL7RA:A",
      "zero_harm": false
    },
    {
      "mean_boltz2_directional_derivative": -0.013590506743639708,
      "mean_oracle_harm_rate": 0.4,
      "mean_protenix_directional_derivative": -5.4242351949214935,
      "mean_step_norm": 0.7840540669858456,
      "mean_worst_oracle_directional_derivative": 0.04637111909687519,
      "method": "contact_qp_grid",
      "method_id": "M8a",
      "num_rows": 4,
      "num_seeds": 4,
      "target": "IL7RA:A",
      "zero_harm": false
    }
  ]
}
